uqid.py
uqid-0.3.0.dist-info/DESCRIPTION.rst
uqid-0.3.0.dist-info/METADATA
uqid-0.3.0.dist-info/RECORD
uqid-0.3.0.dist-info/WHEEL
uqid-0.3.0.dist-info/metadata.json
uqid-0.3.0.dist-info/top_level.txt
