Metadata-Version: 2.0
Name: uqid
Version: 0.3.0
Summary: Unique id from random chars and optional date-time.
Home-page: https://github.com/denis-ryzhkov/uqidpy
Author: Denis Ryzhkov
Author-email: denisr@denisr.com
License: MIT
Platform: UNKNOWN
Classifier: Development Status :: 4 - Beta
Classifier: License :: OSI Approved :: MIT License
Classifier: Operating System :: OS Independent
Classifier: Programming Language :: Python :: 2.7
Classifier: Programming Language :: Python :: 3.5
Classifier: Topic :: Software Development :: Libraries :: Python Modules
